<annotation>
	<folder>data</folder>
	<filename>271.jpg</filename>
	<path>D:\dataset\fyp_data\foodd1\data\271.jpg</path>
	<source>
		<database>Unknown</database>
	</source>
	<size>
		<width>2592</width>
		<height>1944</height>
		<depth>3</depth>
	</size>
	<segmented>0</segmented>
	<object>
		<name>sub</name>
		<pose>Unspecified</pose>
		<truncated>0</truncated>
		<difficult>0</difficult>
		<bndbox>
			<xmin>84</xmin>
			<ymin>654</ymin>
			<xmax>2472</xmax>
			<ymax>1309</ymax>
		</bndbox>
	</object>
</annotation>
